fastkeh/__init__.py
fastkeh/example.py
fastkeh-0.0.1.dist-info/LICENSE
fastkeh-0.0.1.dist-info/METADATA
fastkeh-0.0.1.dist-info/WHEEL
fastkeh-0.0.1.dist-info/top_level.txt
fastkeh-0.0.1.dist-info/RECORD
