Metadata-Version: 2.1
Name: fastkeh
Version: 0.0.1
Summary: webapp joining fastapi and bokeh
Home-page: https://github.com/nestorghenzi/fastkeh
Author: Nestor Ghenzi
Author-email: n.ghenzi@gmail.com
Project-URL: Bug Tracker, https://github.com/nghenzi/fastkeh/issues
Classifier: Programming Language :: Python :: 3
Classifier: License :: OSI Approved :: MIT License
Classifier: Operating System :: OS Independent
Requires-Python: >=3.6
License-File: LICENSE
